pyjokes/__init__.py
pyjokes/jokes_de.py
pyjokes/jokes_en.py
pyjokes/jokes_es.py
pyjokes/jokes_eu.py
pyjokes/jokes_gl.py
pyjokes/jokes_it.py
pyjokes/pyjokes.py
pyjokescli/__init__.py
pyjokescli/pyjoke.py
pyjokescli/pyjokes.py
test_ciautobump-0.0.1.dist-info/LICENCE.txt
test_ciautobump-0.0.1.dist-info/METADATA
test_ciautobump-0.0.1.dist-info/WHEEL
test_ciautobump-0.0.1.dist-info/entry_points.txt
test_ciautobump-0.0.1.dist-info/top_level.txt
test_ciautobump-0.0.1.dist-info/RECORD
