Metadata-Version: 2.1
Name: test-ciautobump
Version: 0.0.1
Summary: One line jokes for programmers (jokes as a service)
Home-page: https://pyjok.es/
Author: Pyjokes Society
Author-email: ben@bennuttall.com
License: BSD License
Keywords: pyjokes,pyjokes,jokes,joke
Platform: ALL
Classifier: Development Status :: 4 - Beta
Classifier: Topic :: Utilities
Classifier: License :: OSI Approved :: BSD License
Classifier: Programming Language :: Python :: 2
Classifier: Programming Language :: Python :: 3
Provides-Extra: doc
Requires-Dist: mkdocs ; extra == 'doc'
Provides-Extra: test
Requires-Dist: pytest ; extra == 'test'
Requires-Dist: coverage ; extra == 'test'
Requires-Dist: tox ; extra == 'test'
